<annotation>
	<folder>scissors</folder>
	<filename>scissors_23.jpg</filename>
	<path>C:\tensorflowupdate\dataset\scissors\scissors_23.jpg</path>
	<source>
		<database>Unknown</database>
	</source>
	<size>
		<width>4328</width>
		<height>3264</height>
		<depth>3</depth>
	</size>
	<segmented>0</segmented>
	<object>
		<name>scissor</name>
		<pose>Unspecified</pose>
		<truncated>0</truncated>
		<difficult>0</difficult>
		<bndbox>
			<xmin>1431</xmin>
			<ymin>1257</ymin>
			<xmax>4206</xmax>
			<ymax>2722</ymax>
		</bndbox>
	</object>
</annotation>
